eiprest/__init__.py
eiprest/__main__.py
eiprest/eiprest.py
tests/__init__.py
tests/test_eiprest.py
eiprest-1.1.dist-info/LICENSE
eiprest-1.1.dist-info/METADATA
eiprest-1.1.dist-info/WHEEL
eiprest-1.1.dist-info/top_level.txt
eiprest-1.1.dist-info/RECORD
