Metadata-Version: 2.1
Name: eiprest
Version: 1.1
Summary: Python module for SOLIDserver REST API
Home-page: https://gitlab.com/charlyhong/eiprest
Author: Charles Hong
Author-email: ch@efficientip.com
License: MIT
Platform: UNKNOWN
Classifier: Programming Language :: Python :: 3
Classifier: License :: OSI Approved :: MIT License
Classifier: Operating System :: OS Independent
Requires-Python: >=3.6
License-File: LICENSE
Requires-Dist: requests
